telehook/__init__.py
telehook/client.py
telehook/filters.py
telehook/methods/__init__.py
telehook/methods/callback_func.py
telehook/methods/edit_func.py
telehook/methods/rpcerror.py
telehook/methods/send_func.py
telehook/types/__init__.py
telehook/types/callback.py
telehook/types/chat.py
telehook/types/keyboard.py
telehook/types/message.py
telehook/types/user.py
telehook/utils/__init__.py
TeleHook-0.2.1.dist-info/LICENSE
TeleHook-0.2.1.dist-info/METADATA
TeleHook-0.2.1.dist-info/WHEEL
TeleHook-0.2.1.dist-info/top_level.txt
TeleHook-0.2.1.dist-info/RECORD
